{
	"Objects": [
{
              "name": "DZ\\plants\\tree\\t_salixalba_2sb_swamp.p3d",
              "pos": [
              12877.131836,
              179.030579,
              4484.638672
            ],
              "ypr": [
              0,
              0,
              0
              ],
              "scale": 1
          },
{
              "name": "DZ\\plants\\tree\\t_robiniapseudoacacia_3f.p3d",
              "pos": [
              12849.478516,
              182.206238,
              4473.149902
            ],
              "ypr": [
              0,
              0,
              0
              ],
              "scale": 1
          },
{
              "name": "DZ\\plants\\tree\\t_robiniapseudoacacia_3f.p3d",
              "pos": [
              12885.886719,
              182.869858,
              4444.855957
            ],
              "ypr": [
              0,
              0,
              0
              ],
              "scale": 1
          },
{
              "name": "DZ\\plants\\tree\\t_robiniapseudoacacia_3f.p3d",
              "pos": [
              12899.649414,
              184.079773,
              4477.42627
            ],
              "ypr": [
              0,
              0,
              0
              ],
              "scale": 1
          },
{
              "name": "DZ\\plants\\tree\\t_robiniapseudoacacia_3f.p3d",
              "pos": [
              12817.164063,
              181.869202,
              4472.820801
            ],
              "ypr": [
              0,
              0,
              0
              ],
              "scale": 1
          },
{
              "name": "DZ\\plants\\tree\\t_quercusrobur_3sb.p3d",
              "pos": [
              12829.0625,
              180.606812,
              4428.838379
            ],
              "ypr": [
              0,
              0,
              0
              ],
              "scale": 1
          },
{
              "name": "DZ\\plants\\tree\\t_quercusrobur_3sb.p3d",
              "pos": [
              12799.449219,
              180.37265,
              4444.217773
            ],
              "ypr": [
              0,
              0,
              0
              ],
              "scale": 1
          },
{
              "name": "DZ\\plants\\tree\\t_quercusrobur_3sb.p3d",
              "pos": [
              12920.041992,
              180.636978,
              4437.717285
            ],
              "ypr": [
              0,
              0,
              0
              ],
              "scale": 1
          },
{
              "name": "DZ\\plants\\tree\\t_quercusrobur_3sb.p3d",
              "pos": [
              12909.189453,
              182.273727,
              4464.655762
            ],
              "ypr": [
              0,
              0,
              0
              ],
              "scale": 1
          },
{
              "name": "DZ\\plants\\tree\\t_quercusrobur_3sb.p3d",
              "pos": [
              12870.767578,
              181.536957,
              4422.022949
            ],
              "ypr": [
              0,
              0,
              0
              ],
              "scale": 1
          },
{
              "name": "DZ\\plants\\tree\\t_quercusrobur_3sb.p3d",
              "pos": [
              12835.446289,
              181.676392,
              4461.662109
            ],
              "ypr": [
              0,
              0,
              0
              ],
              "scale": 1
          },
{
              "name": "DZ\\plants\\tree\\t_quercusrobur_3f.p3d",
              "pos": [
              12861.894531,
              185.108078,
              4460.870605
            ],
              "ypr": [
              0,
              0,
              0
              ],
              "scale": 1
          },
{
              "name": "DZ\\plants\\tree\\t_robiniapseudoacacia_3f.p3d",
              "pos": [
              12866.625977,
              182.624802,
              4456.44873
            ],
              "ypr": [
              0,
              0,
              0
              ],
              "scale": 1
          },
{
              "name": "DZ\\plants\\tree\\t_robiniapseudoacacia_3f.p3d",
              "pos": [
              12871.164063,
              183.478241,
              4477.910156
            ],
              "ypr": [
              0,
              0,
              0
              ],
              "scale": 1
          },
{
              "name": "DZ\\plants\\tree\\t_pyruscommunis_2s.p3d",
              "pos": [
              12887.332031,
              176.205917,
              4452.529297
            ],
              "ypr": [
              0,
              0,
              0
              ],
              "scale": 1
          },
{
              "name": "DZ\\plants\\tree\\t_prunusdomestica_2s.p3d",
              "pos": [
              12894.177734,
              178.020294,
              4460.132324
            ],
              "ypr": [
              0,
              0,
              0
              ],
              "scale": 1
          },
{
              "name": "DZ\\plants\\tree\\t_populusalba_3s.p3d",
              "pos": [
              12899.389648,
              181.107986,
              4443.623535
            ],
              "ypr": [
              0,
              0,
              0
              ],
              "scale": 1
          }
			]
	}